{
  "textures": {
    "outer": "configurablelever:blocks/machine_outer",
    "inner": "configurablelever:blocks/machine_inner"
  },
  "elements": [
    {
      "from": [
        0,
        0,
        0
      ],
      "to": [
        16,
        16,
        16
      ],
      "faces": {
        "down": {
          "uv": [
            16,
            16,
            0,
            0
          ],
          "texture": "#outer"
        },
        "up": {
          "uv": [
            0,
            0,
            16,
            16
          ],
          "texture": "#outer"
        },
        "north": {
          "uv": [
            0,
            0,
            16,
            16
          ],
          "texture": "#outer"
        },
        "south": {
          "uv": [
            0,
            0,
            16,
            16
          ],
          "texture": "#outer"
        },
        "west": {
          "uv": [
            0,
            0,
            16,
            16
          ],
          "texture": "#outer"
        },
        "east": {
          "uv": [
            0,
            0,
            16,
            16
          ],
          "texture": "#outer"
        }
      }
    },
    {
      "from": [
        0,
        0,
        0
      ],
      "to": [
        16,
        16,
        16
      ],
      "faces": {
        "down": {
          "uv": [
            16,
            16,
            0,
            0
          ],
          "texture": "#inner",
          "tintindex": 0
        },
        "up": {
          "uv": [
            0,
            0,
            16,
            16
          ],
          "texture": "#inner",
          "tintindex": 0
        },
        "north": {
          "uv": [
            0,
            0,
            16,
            16
          ],
          "texture": "#inner",
          "tintindex": 0
        },
        "south": {
          "uv": [
            0,
            0,
            16,
            16
          ],
          "texture": "#inner",
          "tintindex": 0
        },
        "west": {
          "uv": [
            0,
            0,
            16,
            16
          ],
          "texture": "#inner",
          "tintindex": 0
        },
        "east": {
          "uv": [
            0,
            0,
            16,
            16
          ],
          "texture": "#inner",
          "tintindex": 0
        }
      }
    }
  ]
}